packrat/__init__.py
packrat/models.py
packrat/settings.py
packrat/storage.py
packrat/urls.py
packrat/views.py
packrat/wsgi.py
packrat/management/__init__.py
packrat/management/commands/__init__.py
packrat/management/commands/update_hoard.py
packrat/migrations/0001_initial.py
packrat/migrations/0002_hoardfile_content_type.py
packrat/migrations/__init__.py
packrat/tests/__init__.py
packrat/tests/models.py
packrat/tests/settings.py
packrat/tests/test_commands.py
packrat/tests/test_models.py
packrat/tests/test_storage.py
packrat/tests/test_views.py
packrat/tests/testfile
packrat-0.2.data/scripts/packrat-daemon
packrat-0.2.data/scripts/packrat-update
packrat-0.2.dist-info/METADATA
packrat-0.2.dist-info/RECORD
packrat-0.2.dist-info/WHEEL
packrat-0.2.dist-info/top_level.txt
packrat-0.2.dist-info/zip-safe
